clingon/__init__.py
clingon/clingon.py
clingon/utils.py
clingon-0.3.2.dist-info/AUTHORS.rst
clingon-0.3.2.dist-info/LICENSE
clingon-0.3.2.dist-info/METADATA
clingon-0.3.2.dist-info/WHEEL
clingon-0.3.2.dist-info/entry_points.txt
clingon-0.3.2.dist-info/top_level.txt
clingon-0.3.2.dist-info/RECORD
