Metadata-Version: 2.1
Name: clingon
Version: 0.3.2
Summary: Command Line INterpreter Generator for pythON
Home-page: https://github.com/francois-vincent/clingon
Author: François Vincent
Author-email: francois.vincent01@gmail.com
License: BSD
Keywords: cli
Classifier: Development Status :: 5 - Production/Stable
Classifier: Intended Audience :: Developers
Classifier: Intended Audience :: System Administrators
Classifier: License :: OSI Approved :: BSD License
Classifier: Natural Language :: English
Classifier: Environment :: Console
Classifier: Programming Language :: Python :: 2
Classifier: Programming Language :: Python :: 2.6
Classifier: Programming Language :: Python :: 2.7
Classifier: Programming Language :: Python :: 3
Classifier: Programming Language :: Python :: 3.3
Classifier: Programming Language :: Python :: 3.4
Classifier: Programming Language :: Python :: 3.5
Classifier: Programming Language :: Python :: Implementation :: CPython
License-File: LICENSE
License-File: AUTHORS.rst
Requires-Dist: future
Requires-Dist: wheel
Requires-Dist: ordereddict ; python_version=="2.6"
